[
  {
    "id": 53,
    "createdAt": "2022-06-24T00:45:51.723Z",
    "updatedAt": "2022-07-25T04:48:26.295Z",
    "deletedAt": null,
    "conveniaId": "4020a524-1fa3-4c22-ac0c-d77d36346b27",
    "conveniaEmployeeId": "2",
    "conveniaEmployeeJob": "49b0b83f-f8f2-4c94-9f2e-d074ae17344d",
    "conveniaPeriodId": "a68de7e8-95ed-4916-9021-1e36367ce763",
    "startsAt": "2022-02-02T19:28:34.976Z",
    "finishesAt": "2022-03-25T03:16:48.632Z",
    "allowance": 3501,
    "thirteenth": false,
    "status": "finished",
    "periodStartedAt": "2022-01-28T07:00:20.980Z",
    "periodFinishedAt": "2022-07-25T11:29:48.742Z",
    "employee": {
      "id": 65,
      "createdAt": "2022-07-25T21:58:47.276Z",
      "updatedAt": "2022-07-25T21:58:47.276Z",
      "name": "Arvilla",
      "lastName": "Schowalter",
      "email": "Phyllis_Kuhic97@yahoo.com",
      "hiredAt": "2022-03-11T04:00:00.000Z",
      "birthDate": "2022-02-04T04:00:00.000Z",
      "departament": "Outdoors",
      "job": "Human Division Coordinator",
      "dismissalAt": "2022-05-29T04:00:00.000Z",
      "avatarImagePath": "https://cdn-icons-png.flaticon.com/512/53/53133.png",
      "conveniaId": "2",
      "pdcLevel": "Doug",
      "quote": "Expedita incidunt at aut voluptas nihil culpa odio architecto consequuntur.",
      "gif": "https://media2.giphy.com/media/cmZ4y6EJWl2MhDCjen/giphy.gif?cid=ecf05e47uia9ctpeke8jbwuyblrmy3o3w3oqhbj6zl9iqslm&rid=giphy.gif&ct=g",
      "slackId": "c0258838-6173-4ace-b67f-2390fcc67318",
      "longitude": -46.6388,
      "latitude": -23.5489
    }
  },
  {
    "id": 57,
    "createdAt": "2022-04-17T02:40:45.649Z",
    "updatedAt": "2022-07-25T03:58:33.366Z",
    "deletedAt": null,
    "conveniaId": "71b7e85c-a560-4089-b7dd-196a6d8387e6",
    "conveniaEmployeeId": "6",
    "conveniaEmployeeJob": "0916794f-e8a8-4362-b10a-b85792ba78fc",
    "conveniaPeriodId": "123551e6-47d5-4afa-97ed-6bdcab977ab4",
    "startsAt": "2021-12-03T04:10:36.585Z",
    "finishesAt": "2022-01-24T19:48:46.166Z",
    "allowance": 8514,
    "thirteenth": false,
    "status": "finished",
    "periodStartedAt": "2021-11-23T09:56:31.605Z",
    "periodFinishedAt": "2022-07-25T06:55:17.647Z",
    "employee": {
      "id": 69,
      "createdAt": "2022-07-25T21:58:47.301Z",
      "updatedAt": "2022-07-25T21:58:47.301Z",
      "name": "Katharina",
      "lastName": "Bogisich",
      "email": "Gabrielle.Davis50@hotmail.com",
      "hiredAt": "2022-01-09T04:00:00.000Z",
      "birthDate": "2022-04-27T04:00:00.000Z",
      "departament": "Beauty",
      "job": "District Accounts Consultant",
      "dismissalAt": "2021-10-14T04:00:00.000Z",
      "avatarImagePath": "https://cdn-icons-png.flaticon.com/512/53/53133.png",
      "conveniaId": "6",
      "pdcLevel": "Bertram",
      "quote": "Aliquam dignissimos iure ratione consequatur quasi tempora blanditiis eum.",
      "gif": "https://media2.giphy.com/media/cmZ4y6EJWl2MhDCjen/giphy.gif?cid=ecf05e47uia9ctpeke8jbwuyblrmy3o3w3oqhbj6zl9iqslm&rid=giphy.gif&ct=g",
      "slackId": "cb4c4f23-8a7b-4342-a3d3-15a21eeec03f",
      "longitude": -46.6388,
      "latitude": -23.5489
    }
  },
  {
    "id": 59,
    "createdAt": "2022-03-25T17:10:53.476Z",
    "updatedAt": "2022-07-24T21:58:16.790Z",
    "deletedAt": null,
    "conveniaId": "c09c22f9-7e62-4f27-b279-486582060dc9",
    "conveniaEmployeeId": "8",
    "conveniaEmployeeJob": "a8479e26-4cc7-457a-8719-b575d4af84d9",
    "conveniaPeriodId": "160be900-ff83-4c2d-9866-facfbc94225c",
    "startsAt": "2022-03-06T06:34:55.813Z",
    "finishesAt": "2022-04-24T22:39:54.088Z",
    "allowance": 4027,
    "thirteenth": false,
    "status": "finished",
    "periodStartedAt": "2022-01-12T13:03:35.095Z",
    "periodFinishedAt": "2022-07-25T08:05:30.308Z",
    "employee": {
      "id": 71,
      "createdAt": "2022-07-25T21:58:47.321Z",
      "updatedAt": "2022-07-25T21:58:47.321Z",
      "name": "Cynthia",
      "lastName": "Hirthe",
      "email": "Hilbert61@hotmail.com",
      "hiredAt": "2021-11-17T04:00:00.000Z",
      "birthDate": "2021-08-10T04:00:00.000Z",
      "departament": "Computers",
      "job": "Legacy Accountability Consultant",
      "dismissalAt": "2021-08-15T04:00:00.000Z",
      "avatarImagePath": "https://cdn-icons-png.flaticon.com/512/53/53133.png",
      "conveniaId": "8",
      "pdcLevel": "Kian",
      "quote": "In sed eveniet dolor deleniti voluptatem ea.",
      "gif": "https://media2.giphy.com/media/cmZ4y6EJWl2MhDCjen/giphy.gif?cid=ecf05e47uia9ctpeke8jbwuyblrmy3o3w3oqhbj6zl9iqslm&rid=giphy.gif&ct=g",
      "slackId": "848baae4-cd8b-40be-add5-b84487a7c603",
      "longitude": -46.6388,
      "latitude": -23.5489
    }
  },
  {
    "id": 61,
    "createdAt": "2021-11-11T10:51:27.566Z",
    "updatedAt": "2022-07-25T12:03:59.285Z",
    "deletedAt": null,
    "conveniaId": "2380fa35-ff2f-4029-9ce6-837d542ee117",
    "conveniaEmployeeId": "10",
    "conveniaEmployeeJob": "5cffb743-8d50-4426-a9ab-a4e1ae664c3a",
    "conveniaPeriodId": "61a0a23b-a615-4592-9324-9dccadc6d732",
    "startsAt": "2022-04-07T18:16:16.353Z",
    "finishesAt": "2022-05-25T15:42:57.860Z",
    "allowance": 15023,
    "thirteenth": false,
    "status": "finished",
    "periodStartedAt": "2021-08-15T12:47:01.546Z",
    "periodFinishedAt": "2022-07-24T18:36:46.335Z",
    "employee": {
      "id": 73,
      "createdAt": "2022-07-25T21:58:47.338Z",
      "updatedAt": "2022-07-25T21:58:47.338Z",
      "name": "Liam",
      "lastName": "Ritchie",
      "email": "Celestino.Abernathy7@hotmail.com",
      "hiredAt": "2022-04-28T04:00:00.000Z",
      "birthDate": "2021-12-16T04:00:00.000Z",
      "departament": "Shoes",
      "job": "Customer Branding Specialist",
      "dismissalAt": "2022-03-23T04:00:00.000Z",
      "avatarImagePath": "https://cdn-icons-png.flaticon.com/512/53/53133.png",
      "conveniaId": "10",
      "pdcLevel": "Emmitt",
      "quote": "Earum molestiae eum excepturi alias unde dolorem.",
      "gif": "https://media2.giphy.com/media/cmZ4y6EJWl2MhDCjen/giphy.gif?cid=ecf05e47uia9ctpeke8jbwuyblrmy3o3w3oqhbj6zl9iqslm&rid=giphy.gif&ct=g",
      "slackId": "da229167-a577-4a2f-b3b0-87d3413f132f",
      "longitude": -46.6388,
      "latitude": -23.5489
    }
  },
  {
    "id": 56,
    "createdAt": "2022-04-23T23:14:48.062Z",
    "updatedAt": "2022-07-25T07:01:34.098Z",
    "deletedAt": null,
    "conveniaId": "941f79ff-c5bd-4668-b98f-b8296aefc9fa",
    "conveniaEmployeeId": "5",
    "conveniaEmployeeJob": "ae9ba992-a0b9-4827-a3ab-924b969ec031",
    "conveniaPeriodId": "b4b4324e-2269-41c5-8075-4e9cf995c65b",
    "startsAt": "2021-05-13T08:40:47.082Z",
    "finishesAt": "2022-06-25T11:31:03.976Z",
    "allowance": 16803,
    "thirteenth": false,
    "status": "finished",
    "periodStartedAt": "2022-06-03T11:06:12.223Z",
    "periodFinishedAt": "2022-07-25T09:09:38.276Z",
    "employee": {
      "id": 68,
      "createdAt": "2022-07-25T21:58:47.296Z",
      "updatedAt": "2022-07-25T21:58:47.296Z",
      "name": "Carlotta",
      "lastName": "Nader",
      "email": "Tatum20@gmail.com",
      "hiredAt": "2022-05-05T04:00:00.000Z",
      "birthDate": "2022-03-16T04:00:00.000Z",
      "departament": "Computers",
      "job": "Internal Identity Administrator",
      "dismissalAt": "2021-12-31T04:00:00.000Z",
      "avatarImagePath": "https://cdn-icons-png.flaticon.com/512/53/53133.png",
      "conveniaId": "5",
      "pdcLevel": "Adonis",
      "quote": "Qui qui ducimus id voluptatum.",
      "gif": "https://media2.giphy.com/media/cmZ4y6EJWl2MhDCjen/giphy.gif?cid=ecf05e47uia9ctpeke8jbwuyblrmy3o3w3oqhbj6zl9iqslm&rid=giphy.gif&ct=g",
      "slackId": "9296ce49-74b6-4a5a-963d-bfce1759f25f",
      "longitude": -46.6388,
      "latitude": -23.5489
    }
  },
  {
    "id": 60,
    "createdAt": "2021-12-12T13:45:55.435Z",
    "updatedAt": "2022-07-24T23:45:53.310Z",
    "deletedAt": null,
    "conveniaId": "8560537c-dfa5-4db8-b304-e24a6cee759c",
    "conveniaEmployeeId": "9",
    "conveniaEmployeeJob": "f77eb3a9-4851-4dea-9571-ccd88eacda9c",
    "conveniaPeriodId": "4fd214a3-132b-4339-84ef-544d9f42dbd7",
    "startsAt": "2023-09-22T22:38:13.047Z",
    "finishesAt": "2023-10-25T09:28:45.622Z",
    "allowance": 15120,
    "thirteenth": false,
    "status": "future",
    "periodStartedAt": "2022-02-18T22:03:57.427Z",
    "periodFinishedAt": "2022-07-25T10:36:37.158Z",
    "employee": {
      "id": 72,
      "createdAt": "2022-07-25T21:58:47.331Z",
      "updatedAt": "2022-07-25T21:58:47.331Z",
      "name": "Eden",
      "lastName": "Tillman",
      "email": "Kiara13@yahoo.com",
      "hiredAt": "2022-03-25T04:00:00.000Z",
      "birthDate": "2022-03-16T04:00:00.000Z",
      "departament": "Beauty",
      "job": "Central Metrics Representative",
      "dismissalAt": "2022-06-17T04:00:00.000Z",
      "avatarImagePath": "https://cdn-icons-png.flaticon.com/512/53/53133.png",
      "conveniaId": "9",
      "pdcLevel": "Jamil",
      "quote": "Vero sed odio debitis cum.",
      "gif": "https://media2.giphy.com/media/cmZ4y6EJWl2MhDCjen/giphy.gif?cid=ecf05e47uia9ctpeke8jbwuyblrmy3o3w3oqhbj6zl9iqslm&rid=giphy.gif&ct=g",
      "slackId": "d4fe66c6-8da4-42a3-9de6-28fb7653f6f8",
      "longitude": -46.6388,
      "latitude": -23.5489
    }
  },
  {
    "id": 54,
    "createdAt": "2021-11-13T22:19:30.589Z",
    "updatedAt": "2022-07-25T15:07:03.480Z",
    "deletedAt": null,
    "conveniaId": "fdffd6b8-af22-4dec-8781-e486be60ff6d",
    "conveniaEmployeeId": "3",
    "conveniaEmployeeJob": "927e46e4-41f4-4f61-83bc-898d531a56d5",
    "conveniaPeriodId": "e99f8a07-4252-4fd5-a8fa-42afbb7e3b7b",
    "startsAt": "2022-06-26T16:15:47.629Z",
    "finishesAt": "2022-08-25T02:58:50.643Z",
    "allowance": 8616,
    "thirteenth": false,
    "status": "ongoing",
    "periodStartedAt": "2021-11-29T09:47:39.111Z",
    "periodFinishedAt": "2022-07-24T18:15:45.228Z",
    "employee": {
      "id": 66,
      "createdAt": "2022-07-25T21:58:47.283Z",
      "updatedAt": "2022-07-25T21:58:47.283Z",
      "name": "Elnora",
      "lastName": "Ziemann",
      "email": "Kayli94@yahoo.com",
      "hiredAt": "2022-02-01T04:00:00.000Z",
      "birthDate": "2022-03-05T04:00:00.000Z",
      "departament": "Outdoors",
      "job": "National Division Engineer",
      "dismissalAt": "2021-09-01T04:00:00.000Z",
      "avatarImagePath": "https://cdn-icons-png.flaticon.com/512/53/53133.png",
      "conveniaId": "3",
      "pdcLevel": "Hilda",
      "quote": "Dolores ut rerum et consequuntur.",
      "gif": "https://media2.giphy.com/media/cmZ4y6EJWl2MhDCjen/giphy.gif?cid=ecf05e47uia9ctpeke8jbwuyblrmy3o3w3oqhbj6zl9iqslm&rid=giphy.gif&ct=g",
      "slackId": "9b3c9acd-e439-4d5d-85a3-d723e3fdc87f",
      "longitude": -46.6388,
      "latitude": -23.5489
    }
  },
  {
    "id": 55,
    "createdAt": "2022-06-09T19:45:25.596Z",
    "updatedAt": "2022-07-25T13:48:54.839Z",
    "deletedAt": null,
    "conveniaId": "d4672d39-4606-4b54-9dc2-ce287d1314cc",
    "conveniaEmployeeId": "4",
    "conveniaEmployeeJob": "ebfae7eb-4ed8-4568-94a6-60c493100a95",
    "conveniaPeriodId": "13a29529-2fd5-4788-9a07-495c35429198",
    "startsAt": "2022-06-26T16:15:47.629Z",
    "finishesAt": "2022-08-26T16:15:47.629Z",
    "allowance": 8023,
    "thirteenth": false,
    "status": "ongoing",
    "periodStartedAt": "2022-02-18T01:53:30.926Z",
    "periodFinishedAt": "2022-07-25T11:51:41.641Z",
    "employee": {
      "id": 67,
      "createdAt": "2022-07-25T21:58:47.290Z",
      "updatedAt": "2022-07-25T21:58:47.290Z",
      "name": "Janet",
      "lastName": "Huel",
      "email": "Albertha66@gmail.com",
      "hiredAt": "2021-09-14T04:00:00.000Z",
      "birthDate": "2022-04-15T04:00:00.000Z",
      "departament": "Shoes",
      "job": "Human Creative Director",
      "dismissalAt": "2021-11-15T04:00:00.000Z",
      "avatarImagePath": "https://cdn-icons-png.flaticon.com/512/53/53133.png",
      "conveniaId": "4",
      "pdcLevel": "Columbus",
      "quote": "Facilis id temporibus a ut.",
      "gif": "https://media2.giphy.com/media/cmZ4y6EJWl2MhDCjen/giphy.gif?cid=ecf05e47uia9ctpeke8jbwuyblrmy3o3w3oqhbj6zl9iqslm&rid=giphy.gif&ct=g",
      "slackId": "06e1ff3c-d577-4215-bfda-e1884ba0ee3c",
      "longitude": -46.6388,
      "latitude": -23.5489
    }
  },
  {
    "id": 58,
    "createdAt": "2022-03-22T09:44:59.038Z",
    "updatedAt": "2022-07-25T14:14:23.105Z",
    "deletedAt": null,
    "conveniaId": "cb55a1fd-f029-44a9-90ee-3e99dd031a34",
    "conveniaEmployeeId": "7",
    "conveniaEmployeeJob": "e9a8a060-9fa3-450f-93ad-ba5f69ecb726",
    "conveniaPeriodId": "642e71dc-e758-46c5-97ff-d7908b114d45",
    "startsAt": "2022-07-26T06:15:47.629Z",
    "finishesAt": "2022-07-28T02:58:50.643Z",
    "allowance": 3507,
    "thirteenth": false,
    "status": "ongoing",
    "periodStartedAt": "2022-01-02T07:34:17.056Z",
    "periodFinishedAt": "2022-07-25T04:24:38.378Z",
    "employee": {
      "id": 70,
      "createdAt": "2022-07-25T21:58:47.311Z",
      "updatedAt": "2022-07-25T21:58:47.311Z",
      "name": "Ettie",
      "lastName": "Blanda",
      "email": "Annabell_Raynor0@gmail.com",
      "hiredAt": "2021-12-22T04:00:00.000Z",
      "birthDate": "2022-01-26T04:00:00.000Z",
      "departament": "Garden",
      "job": "Central Applications Associate",
      "dismissalAt": "2021-07-27T04:00:00.000Z",
      "avatarImagePath": "https://cdn-icons-png.flaticon.com/512/53/53133.png",
      "conveniaId": "7",
      "pdcLevel": "Shanon",
      "quote": "Expedita sint rerum minus qui.",
      "gif": "https://media2.giphy.com/media/cmZ4y6EJWl2MhDCjen/giphy.gif?cid=ecf05e47uia9ctpeke8jbwuyblrmy3o3w3oqhbj6zl9iqslm&rid=giphy.gif&ct=g",
      "slackId": "84a635b9-1c8d-45b3-9447-cfb7376c85b4",
      "longitude": -46.6388,
      "latitude": -23.5489
    }
  },
  {
    "id": 52,
    "createdAt": "2021-10-29T12:58:46.665Z",
    "updatedAt": "2022-07-25T17:11:44.521Z",
    "deletedAt": null,
    "conveniaId": "955e8319-381b-4f3f-a319-ad5c9c67a053",
    "conveniaEmployeeId": "1",
    "conveniaEmployeeJob": "a092c1d4-58e0-47df-8438-c954a83b0df5",
    "conveniaPeriodId": "e8734253-8c8a-401f-9d95-c59f1b509574",
    "startsAt": "2022-01-23T16:47:37.998Z",
    "finishesAt": "2022-02-25T07:51:39.439Z",
    "allowance": 16165,
    "thirteenth": false,
    "status": "finished",
    "periodStartedAt": "2021-08-12T01:19:21.357Z",
    "periodFinishedAt": "2022-07-25T01:06:33.942Z",
    "employee": {
      "id": 64,
      "createdAt": "2022-07-25T21:58:47.245Z",
      "updatedAt": "2022-07-25T21:58:47.245Z",
      "name": "Odell",
      "lastName": "Keebler",
      "email": "Dane.Schoen34@gmail.com",
      "hiredAt": "2022-06-25T04:00:00.000Z",
      "birthDate": "2022-07-22T04:00:00.000Z",
      "departament": "Beauty",
      "job": "Legacy Response Designer",
      "dismissalAt": "2022-06-03T04:00:00.000Z",
      "avatarImagePath": "https://cdn-icons-png.flaticon.com/512/53/53133.png",
      "conveniaId": "1",
      "pdcLevel": "Emmanuel",
      "quote": "Placeat nulla dolorem harum et voluptate id nobis eos.",
      "gif": "https://media2.giphy.com/media/cmZ4y6EJWl2MhDCjen/giphy.gif?cid=ecf05e47uia9ctpeke8jbwuyblrmy3o3w3oqhbj6zl9iqslm&rid=giphy.gif&ct=g",
      "slackId": "28592662-adc1-4e30-ad4f-5cad392b0430",
      "longitude": -46.6388,
      "latitude": -23.5489
    }
  }
]
